finish_sound/__init__.py
finish_sound/sounds/aussie-finish-sound.mp3
finish_sound/sounds/british-finish-sound.mp3
finish_sound/sounds/deep-finish-sound.mp3
finish_sound/sounds/prabhat-finish-sound.mp3
finish_sound-0.1.3.dist-info/LICENSE
finish_sound-0.1.3.dist-info/METADATA
finish_sound-0.1.3.dist-info/WHEEL
finish_sound-0.1.3.dist-info/top_level.txt
finish_sound-0.1.3.dist-info/RECORD
