Metadata-Version: 2.1
Name: finish-sound
Version: 0.1.3
Summary: A simple package that plays a sound when code finishes running
Home-page: https://github.com/kentjliu/finish-sound
Author: Your Name
Author-email: your.email@example.com
Classifier: Programming Language :: Python :: 3
Classifier: License :: OSI Approved :: MIT License
Classifier: Operating System :: OS Independent
Requires-Python: >=3.6
License-File: LICENSE
Requires-Dist: playsound>=1.2.2
Requires-Dist: pygame>=2.0.1
Requires-Dist: pydub>=0.25.1
Requires-Dist: IPython>=7.0
